prefer_extension/__init__.py
prefer_extension/cli.py
prefer_extension-0.1.1.dist-info/entry_points.txt
prefer_extension-0.1.1.dist-info/WHEEL
prefer_extension-0.1.1.dist-info/METADATA
prefer_extension-0.1.1.dist-info/RECORD
