Metadata-Version: 2.1
Name: prefer-extension
Version: 0.1.1
Summary: 
Author: Brian Sunter
Author-email: brian@briansunter.com
Requires-Python: >=3.7,<4.0
Classifier: Programming Language :: Python :: 3
Classifier: Programming Language :: Python :: 3.7
Classifier: Programming Language :: Python :: 3.8
Requires-Dist: click (>=7.1.1,<8.0.0)
Requires-Dist: funcy (>=1.14,<2.0)
